<xml><variables><variable type="" id="wr0DZaJETw6Hz!cU^Q/h">vr</variable><variable type="" id="AQ32~:5i.QHsa9JIkl+[">deb</variable></variables><block type="graph_set_r" id="u2am$`zU3TF)BUY@wp`0" deletable="false" x="9" y="21"><value name="VALUE"><block type="logic_ternary" id="kT`x$!vfxp9z#r6.kqAr"><value name="IF"><block type="logic_compare" id="9wl]O9@-ZG_$Uk3;]#!z"><field name="OP">NEQ</field><value name="A"><block type="variables_get" id="W%a*xX3;fX)Xx2w7pCEm"><field name="VAR" id="AQ32~:5i.QHsa9JIkl+[" variabletype="">deb</field></block></value><value name="B"><block type="math_number" id="~T!@43Bo._c}}ft0_$[$"><field name="NUM">1</field></block></value></block></value><value name="THEN"><block type="procedures_callreturn" id="#sl?~=Q4)#D(X+6iS+v_"><mutation name="xr"></mutation></block></value><value name="ELSE"><block type="variables_get" id="7gX_2RmlLmIK!jW}(%eO"><field name="VAR" id="wr0DZaJETw6Hz!cU^Q/h" variabletype="">vr</field></block></value></block></value></block><block type="procedures_defreturn" id="TP33i27t`Gql78aCTiP8" x="555" y="18"><field name="NAME">xr</field><comment pinned="false" h="80" w="160">Describe this function...</comment><statement name="STACK"><block type="procedures_callnoreturn" id="gTR|D;VW;`X6:]x.#8F6"><mutation name="main"></mutation></block></statement><value name="RETURN"><block type="variables_get" id="c.OVc9.?[%#/r2Vc0XMT"><field name="VAR" id="wr0DZaJETw6Hz!cU^Q/h" variabletype="">vr</field></block></value></block><block type="procedures_defreturn" id="R+UBsrwou=2@Cb=Sl[Uh" x="765" y="21"><field name="NAME">xg</field><comment pinned="false" h="80" w="160">Describe this function...</comment><statement name="STACK"><block type="procedures_callnoreturn" id="kgWkx!~h^OTbuRh~f,.#"><mutation name="main"></mutation></block></statement><value name="RETURN"><block type="variables_get" id="x~9TUfnmBpae*DW_3QAs"><field name="VAR" id="wr0DZaJETw6Hz!cU^Q/h" variabletype="">vr</field></block></value></block><block type="procedures_defreturn" id="B?,Py7umNRT/~9rlg!WC" x="990" y="28"><field name="NAME">xb</field><comment pinned="false" h="80" w="160">Describe this function...</comment><statement name="STACK"><block type="procedures_callnoreturn" id=":nWop[e[~f:lcMiR^=sO"><mutation name="main"></mutation></block></statement><value name="RETURN"><block type="variables_get" id="2lwz#+DfJsZylhbC^X33"><field name="VAR" id="wr0DZaJETw6Hz!cU^Q/h" variabletype="">vr</field></block></value></block><block type="procedures_defnoreturn" id="og9iMUqdnUTrpY8Ky%+A" x="-323" y="125"><field name="NAME">main</field><comment pinned="false" h="80" w="160">Describe this function...</comment><statement name="STACK"><block type="variables_set" id="oR3EQSF/L6PJLX`L,Ue|"><field name="VAR" id="wr0DZaJETw6Hz!cU^Q/h" variabletype="">vr</field><value name="VALUE"><block type="math_arithmetic" id="[}36oe0/n0yflKw[LD+;"><field name="OP">DIVIDE</field><value name="A"><shadow type="math_number" id="#z)RNvy.p$y(jiOYtgUH"><field name="NUM">1</field></shadow><block type="math_arithmetic" id="MaH1Qf%7`-wzm0l([0rb"><field name="OP">ADD</field><value name="A"><shadow type="math_number"><field name="NUM">1</field></shadow><block type="graph_get_r" id="@RMUM,.f[CAwFJfdWQ+j"></block></value><value name="B"><shadow type="math_number"><field name="NUM">1</field></shadow><block type="math_arithmetic" id="R$[^}gAaF;B+U7{Fq{Yb"><field name="OP">ADD</field><value name="A"><shadow type="math_number"><field name="NUM">1</field></shadow><block type="graph_get_g" id="p{e)o5i~M;x0AE~1f[(T"></block></value><value name="B"><shadow type="math_number" id="y=JA;YV%$Ua]EcQSZRqn"><field name="NUM">1</field></shadow><block type="graph_get_b" id="[6/2g.U$xPaq:S[7Ocu}"></block></value></block></value></block></value><value name="B"><shadow type="math_number" id="nVj{Cw0twQqHI@wh[M39"><field name="NUM">3</field></shadow></value></block></value><next><block type="variables_set" id="g+{bF^AcoTAkjGxfHbYw"><field name="VAR" id="AQ32~:5i.QHsa9JIkl+[" variabletype="">deb</field><value name="VALUE"><block type="math_number" id="nPD)8+dq=*+=X$GLhWk_"><field name="NUM">1</field></block></value></block></next></block></statement></block><block type="graph_set_g" id="$;+gLo%w#g2*(w88_ldd" deletable="false" x="335" y="110"><value name="VALUE"><block type="logic_ternary" id="ok~NQ,,I~f!Uq=#;gw~f"><value name="IF"><block type="logic_compare" id="Jd]fZ!~RZ[yAHN%fFW?^"><field name="OP">NEQ</field><value name="A"><block type="variables_get" id="s5hr%+G@f@$g3i7$ONE^"><field name="VAR" id="AQ32~:5i.QHsa9JIkl+[" variabletype="">deb</field></block></value><value name="B"><block type="math_number" id="Ew%TjDlMm_m;|T%|)z:]"><field name="NUM">1</field></block></value></block></value><value name="THEN"><block type="procedures_callreturn" id=";SlYs*GLT;%1+*m`Usd)"><mutation name="xg"></mutation></block></value><value name="ELSE"><block type="variables_get" id="9i},6+}hE6x`y~+qM=(}"><field name="VAR" id="wr0DZaJETw6Hz!cU^Q/h" variabletype="">vr</field></block></value></block></value></block><block type="graph_set_b" id="c~):9[y[Q{UPhgb:BVK[" deletable="false" x="100" y="240"><value name="VALUE"><block type="logic_ternary" id="eai,By,@LzUVRYzL+%G7"><value name="IF"><block type="logic_compare" id=")Gdmaaqu%OIhjy%`9f}H"><field name="OP">NEQ</field><value name="A"><block type="variables_get" id="QVC91q|wU|l}v@rX2)M["><field name="VAR" id="AQ32~:5i.QHsa9JIkl+[" variabletype="">deb</field></block></value><value name="B"><block type="math_number" id=".Lw|WA`d)P9htd)fecmA"><field name="NUM">1</field></block></value></block></value><value name="THEN"><block type="procedures_callreturn" id="^9kT.~`nO7?#/Y={/pRD"><mutation name="xb"></mutation></block></value><value name="ELSE"><block type="variables_get" id="-|p*8MA?SEG#}s/]|aB6"><field name="VAR" id="wr0DZaJETw6Hz!cU^Q/h" variabletype="">vr</field></block></value></block></value></block></xml>